zc.zservertracelog-3.0-py3.9-nspkg.pth
zc/zservertracelog/README.rst
zc/zservertracelog/__init__.py
zc/zservertracelog/configure.zcml
zc/zservertracelog/fseek.py
zc/zservertracelog/interfaces.py
zc/zservertracelog/tests.py
zc/zservertracelog/tracelog.py
zc/zservertracelog/tracereport.py
zc/zservertracelog/tracereport.rst
zc/zservertracelog/samples/trace.log
zc.zservertracelog-3.0.dist-info/LICENSE.rst
zc.zservertracelog-3.0.dist-info/METADATA
zc.zservertracelog-3.0.dist-info/WHEEL
zc.zservertracelog-3.0.dist-info/entry_points.txt
zc.zservertracelog-3.0.dist-info/namespace_packages.txt
zc.zservertracelog-3.0.dist-info/top_level.txt
zc.zservertracelog-3.0.dist-info/RECORD
