Metadata-Version: 2.1
Name: zc.zservertracelog
Version: 3.0
Summary: Zope 3 tracelog implementation for zserver
Home-page: https://github.com/zopefoundation/zc.zservertracelog
Author: Zope Corporation and Contributors
Author-email: zope3-dev@zope.org
License: ZPL 2.1
Keywords: zope3
Classifier: Development Status :: 4 - Beta
Classifier: Programming Language :: Python :: 3.7
Classifier: Programming Language :: Python :: 3.8
Classifier: Programming Language :: Python :: 3.9
Classifier: Programming Language :: Python :: 3.10
Classifier: Programming Language :: Python :: 3.11
Classifier: Programming Language :: Python :: Implementation :: CPython
Classifier: Programming Language :: Python :: Implementation :: PyPy
Requires-Python: >=3.7
License-File: LICENSE.rst
Requires-Dist: setuptools
Requires-Dist: zope.app.appsetup
Requires-Dist: zope.app.server
Requires-Dist: zope.app.wsgi
Requires-Dist: zope.component
Requires-Dist: zope.interface
Requires-Dist: zope.publisher
Requires-Dist: zope.server
Provides-Extra: test
Requires-Dist: manuel ; extra == 'test'
Requires-Dist: zope.testing ; extra == 'test'
Requires-Dist: zope.testrunner ; extra == 'test'
